MANIFEST.in
setup.py
django_social_auth_trello/__init__.py
django_social_auth_trello/backend.py
django_social_auth_trello.egg-info/PKG-INFO
django_social_auth_trello.egg-info/SOURCES.txt
django_social_auth_trello.egg-info/dependency_links.txt
django_social_auth_trello.egg-info/requires.txt
django_social_auth_trello.egg-info/top_level.txt