Metadata-Version: 1.0
Name: django-social-auth-trello
Version: 1.0.2
Summary: A Sentry plugin that integrates with Trello
Home-page: https://github.com/DamianZaremba/django-social-auth-trello
Author: Damian Zaremba
Author-email: damian@damianzaremba.co.uk
License: GPL
Platform: UNKNOWN
